directedgraph/__init__.py
directedgraph/directed_graph.py
directedgraph/version.py
directedgraph-0.0.1.dist-info/DESCRIPTION.rst
directedgraph-0.0.1.dist-info/METADATA
directedgraph-0.0.1.dist-info/RECORD
directedgraph-0.0.1.dist-info/WHEEL
directedgraph-0.0.1.dist-info/metadata.json
directedgraph-0.0.1.dist-info/top_level.txt
tests/__init__.py
tests/test.py
